{
  "$schema": "https://ui.shadcn.com/schema/registry-item.json",
  "name": "p-breadcrumb-1",
  "description": "Breadcrumb with menu example",
  "registryDependencies": [
    "@coss/breadcrumb",
    "@coss/button",
    "@coss/menu"
  ],
  "files": [
    {
      "path": "registry/default/particles/p-breadcrumb-1.tsx",
      "content": "import Link from \"next/link\";\r\nimport {\r\n  Breadcrumb,\r\n  BreadcrumbEllipsis,\r\n  BreadcrumbItem,\r\n  BreadcrumbLink,\r\n  BreadcrumbList,\r\n  BreadcrumbPage,\r\n  BreadcrumbSeparator,\r\n} from \"@/registry/default/ui/breadcrumb\";\r\nimport { Button } from \"@/registry/default/ui/button\";\r\nimport {\r\n  Menu,\r\n  MenuItem,\r\n  MenuPopup,\r\n  MenuTrigger,\r\n} from \"@/registry/default/ui/menu\";\r\n\r\nexport default function Particle() {\r\n  return (\r\n    <Breadcrumb>\r\n      <BreadcrumbList>\r\n        <BreadcrumbItem>\r\n          <BreadcrumbLink render={<Link href=\"/\" />}>Home</BreadcrumbLink>\r\n        </BreadcrumbItem>\r\n        <BreadcrumbSeparator />\r\n        <BreadcrumbItem>\r\n          <Menu>\r\n            <MenuTrigger\r\n              render={\r\n                <Button\r\n                  className=\"-m-1.5 text-muted-foreground\"\r\n                  size=\"icon-sm\"\r\n                  variant=\"ghost\"\r\n                />\r\n              }\r\n            >\r\n              <BreadcrumbEllipsis />\r\n            </MenuTrigger>\r\n            <MenuPopup align=\"start\">\r\n              <MenuItem render={<Link href=\"/docs\" />}>Docs</MenuItem>\r\n              <MenuItem render={<Link href=\"/particles\" />}>Particles</MenuItem>\r\n            </MenuPopup>\r\n          </Menu>\r\n        </BreadcrumbItem>\r\n        <BreadcrumbSeparator />\r\n        <BreadcrumbItem>\r\n          <BreadcrumbLink render={<Link href=\"/docs/\" />}>\r\n            Components\r\n          </BreadcrumbLink>\r\n        </BreadcrumbItem>\r\n        <BreadcrumbSeparator />\r\n        <BreadcrumbItem>\r\n          <BreadcrumbPage>Breadcrumb</BreadcrumbPage>\r\n        </BreadcrumbItem>\r\n      </BreadcrumbList>\r\n    </Breadcrumb>\r\n  );\r\n}\r\n",
      "type": "registry:block"
    }
  ],
  "categories": [
    "breadcrumb",
    "dropdown",
    "menu"
  ],
  "type": "registry:block"
}