{
  "$schema": "https://ui.shadcn.com/schema/registry-item.json",
  "name": "p-button-36",
  "description": "Copy button with feedback",
  "dependencies": [
    "lucide-react"
  ],
  "registryDependencies": [
    "@coss/button"
  ],
  "files": [
    {
      "path": "registry/default/particles/p-button-36.tsx",
      "content": "\"use client\";\r\n\r\nimport { CheckIcon, CopyIcon } from \"lucide-react\";\r\nimport { useState } from \"react\";\r\nimport { Button } from \"@/registry/default/ui/button\";\r\n\r\nexport default function Particle() {\r\n  const [copied, setCopied] = useState(false);\r\n\r\n  const handleCopy = () => {\r\n    navigator.clipboard.writeText(\"Text copied!\");\r\n    setCopied(true);\r\n    setTimeout(() => setCopied(false), 2000);\r\n  };\r\n\r\n  return (\r\n    <Button onClick={handleCopy} variant=\"outline\">\r\n      {copied ? (\r\n        <>\r\n          <CheckIcon aria-hidden=\"true\" />\r\n          Copied\r\n        </>\r\n      ) : (\r\n        <>\r\n          <CopyIcon aria-hidden=\"true\" />\r\n          Copy\r\n        </>\r\n      )}\r\n    </Button>\r\n  );\r\n}\r\n",
      "type": "registry:block"
    }
  ],
  "categories": [
    "button"
  ],
  "type": "registry:block"
}