{
  "$schema": "https://ui.shadcn.com/schema/registry-item.json",
  "name": "p-slider-16",
  "description": "Emoji rating slider",
  "registryDependencies": [
    "@coss/field",
    "@coss/slider"
  ],
  "files": [
    {
      "path": "registry/default/particles/p-slider-16.tsx",
      "content": "\"use client\";\r\n\r\nimport { useState } from \"react\";\r\nimport { Field, FieldLabel } from \"@/registry/default/ui/field\";\r\nimport { Slider } from \"@/registry/default/ui/slider\";\r\n\r\nconst labels = [\"Awful\", \"Poor\", \"Okay\", \"Good\", \"Amazing\"];\r\n\r\nexport default function Particle() {\r\n  const [value, setValue] = useState<number | readonly number[]>(3);\r\n\r\n  const currentValue = Array.isArray(value) ? value[0] : value;\r\n\r\n  return (\r\n    <Field className=\"*:grid *:grid-cols-[auto_1fr_auto] *:items-center *:gap-x-2\">\r\n      <Slider\r\n        aria-label=\"Rate your experience\"\r\n        max={5}\r\n        min={1}\r\n        onValueChange={setValue}\r\n        value={value}\r\n      >\r\n        <div className=\"col-span-3 mb-2 flex items-center justify-between gap-1\">\r\n          <FieldLabel>Rate your experience</FieldLabel>\r\n          <span className=\"text-sm\">{labels[currentValue - 1]}</span>\r\n        </div>\r\n        <span aria-hidden=\"true\" className=\"text-2xl\">\r\n          😡\r\n        </span>\r\n        <span aria-hidden=\"true\" className=\"order-1 text-2xl\">\r\n          😍\r\n        </span>\r\n      </Slider>\r\n    </Field>\r\n  );\r\n}\r\n",
      "type": "registry:block"
    }
  ],
  "meta": {
    "className": "**:data-[slot=preview]:w-full **:data-[slot=preview]:max-w-64"
  },
  "categories": [
    "slider"
  ],
  "type": "registry:block"
}