{
  "$schema": "https://ui.shadcn.com/schema/registry-item.json",
  "name": "p-slider-4",
  "description": "Slider with reference labels",
  "registryDependencies": [
    "@coss/slider"
  ],
  "files": [
    {
      "path": "registry/default/particles/p-slider-4.tsx",
      "content": "import { Slider } from \"@/registry/default/ui/slider\";\r\n\r\nexport default function Particle() {\r\n  return (\r\n    <div>\r\n      <Slider\r\n        aria-label=\"Storage size in GB\"\r\n        defaultValue={15}\r\n        max={35}\r\n        min={5}\r\n      />\r\n      <div\r\n        aria-label=\"Storage size reference values\"\r\n        className=\"mt-4 flex w-full items-center justify-between gap-1 font-medium text-muted-foreground text-xs\"\r\n        role=\"group\"\r\n      >\r\n        <span>5 GB</span>\r\n        <span>20 GB</span>\r\n        <span>35 GB</span>\r\n      </div>\r\n    </div>\r\n  );\r\n}\r\n",
      "type": "registry:block"
    }
  ],
  "meta": {
    "className": "**:data-[slot=preview]:w-full **:data-[slot=preview]:max-w-64"
  },
  "categories": [
    "slider"
  ],
  "type": "registry:block"
}