{
  "$schema": "https://ui.shadcn.com/schema/registry-item.json",
  "name": "p-toggle-group-5",
  "description": "Vertical toggle group with outline",
  "registryDependencies": [
    "@coss/toggle-group"
  ],
  "files": [
    {
      "path": "registry/default/particles/p-toggle-group-5.tsx",
      "content": "import { BoldIcon, ItalicIcon, UnderlineIcon } from \"lucide-react\";\r\nimport {\r\n  ToggleGroup,\r\n  ToggleGroupItem,\r\n  ToggleGroupSeparator,\r\n} from \"@/registry/default/ui/toggle-group\";\r\n\r\nexport default function Particle() {\r\n  return (\r\n    <ToggleGroup\r\n      defaultValue={[\"bold\"]}\r\n      orientation=\"vertical\"\r\n      variant=\"outline\"\r\n    >\r\n      <ToggleGroupItem aria-label=\"Toggle bold\" value=\"bold\">\r\n        <BoldIcon />\r\n      </ToggleGroupItem>\r\n      <ToggleGroupSeparator orientation=\"horizontal\" />\r\n      <ToggleGroupItem aria-label=\"Toggle italic\" value=\"italic\">\r\n        <ItalicIcon />\r\n      </ToggleGroupItem>\r\n      <ToggleGroupSeparator orientation=\"horizontal\" />\r\n      <ToggleGroupItem aria-label=\"Toggle underline\" value=\"underline\">\r\n        <UnderlineIcon />\r\n      </ToggleGroupItem>\r\n    </ToggleGroup>\r\n  );\r\n}\r\n",
      "type": "registry:block"
    }
  ],
  "categories": [
    "toggle",
    "toggle group"
  ],
  "type": "registry:block"
}