{
  "$schema": "https://ui.shadcn.com/schema/registry-item.json",
  "name": "comp-500",
  "type": "registry:component",
  "registryDependencies": [
    "https://coss.com/origin/r/button.json",
    "https://coss.com/origin/r/calendar.json"
  ],
  "files": [
    {
      "path": "registry/default/components/comp-500.tsx",
      "content": "\"use client\";\n\nimport { addDays } from \"date-fns\";\nimport { useState } from \"react\";\n\nimport { Button } from \"@/registry/default/ui/button\";\nimport { Calendar } from \"@/registry/default/ui/calendar\";\n\nexport default function Component() {\n  const today = new Date();\n  const selectedDay = addDays(today, -28);\n  const [month, setMonth] = useState(selectedDay);\n  const [date, setDate] = useState<Date | undefined>(selectedDay);\n\n  return (\n    <div>\n      <div className=\"rounded-md border p-2\">\n        <Calendar\n          mode=\"single\"\n          month={month}\n          onMonthChange={setMonth}\n          onSelect={setDate}\n          selected={date}\n        />\n        <Button\n          className=\"mt-2 mb-1\"\n          onClick={() => setMonth(today)}\n          size=\"sm\"\n          variant=\"outline\"\n        >\n          Current month\n        </Button>\n      </div>\n      <p\n        aria-live=\"polite\"\n        className=\"mt-4 text-center text-muted-foreground text-xs\"\n        role=\"region\"\n      >\n        With button -{\" \"}\n        <a\n          className=\"underline hover:text-foreground\"\n          href=\"https://daypicker.dev/\"\n          rel=\"noreferrer noopener nofollow\"\n          target=\"_blank\"\n        >\n          React DayPicker\n        </a>\n      </p>\n    </div>\n  );\n}\n",
      "type": "registry:component"
    }
  ],
  "meta": {
    "style": 1,
    "tags": [
      "calendar",
      "date",
      "button",
      "react daypicker"
    ]
  }
}